doug/__init__.py
doug/utils/longside_resize.cpython-36m-x86_64-linux-gnu.so
doug/utils/gaussian.cpython-36m-x86_64-linux-gnu.so
doug/utils/visualize.cpython-36m-x86_64-linux-gnu.so
doug/utils/kp2mask.cpython-36m-x86_64-linux-gnu.so
doug/utils/mask2bbox.cpython-36m-x86_64-linux-gnu.so
doug/utils/__init__.cpython-36m-x86_64-linux-gnu.so
doug/utils/fill_in.cpython-36m-x86_64-linux-gnu.so
doug/utils/zoom_in.cpython-36m-x86_64-linux-gnu.so
doug/utils/__init__.py
doug/utils/polygon2aabb.cpython-36m-x86_64-linux-gnu.so
doug/utils/gaussian_v2.cpython-36m-x86_64-linux-gnu.so
doug/utils/lightspace.cpython-36m-x86_64-linux-gnu.so
doug/core/zoom_one_class.cpython-36m-x86_64-linux-gnu.so
doug/core/night_noise.cpython-36m-x86_64-linux-gnu.so
doug/core/sample_function.cpython-36m-x86_64-linux-gnu.so
doug/core/vertical_light_gradient.cpython-36m-x86_64-linux-gnu.so
doug/core/copy_paste_under.cpython-36m-x86_64-linux-gnu.so
doug/core/fix_jpgmask.cpython-36m-x86_64-linux-gnu.so
doug/core/delete_one_class.cpython-36m-x86_64-linux-gnu.so
doug/core/horizontal_light_gradient.cpython-36m-x86_64-linux-gnu.so
doug/core/occlusion_paste_above.cpython-36m-x86_64-linux-gnu.so
doug/core/__init__.cpython-36m-x86_64-linux-gnu.so
doug/core/zoom_classes.cpython-36m-x86_64-linux-gnu.so
doug/core/add_watermark.cpython-36m-x86_64-linux-gnu.so
doug/core/tremor.cpython-36m-x86_64-linux-gnu.so
doug/core/small_angle_rotate.cpython-36m-x86_64-linux-gnu.so
doug/core/delete_classes.cpython-36m-x86_64-linux-gnu.so
doug/core/night_light_spot.cpython-36m-x86_64-linux-gnu.so
doug/core/__init__.py
doug/core/DouG.cpython-36m-x86_64-linux-gnu.so
doug/core/hsv_color.cpython-36m-x86_64-linux-gnu.so
doug-0.1.0.dist-info/WHEEL
doug-0.1.0.dist-info/METADATA
doug-0.1.0.dist-info/top_level.txt
doug-0.1.0.dist-info/RECORD
