Metadata-Version: 2.1
Name: doug
Version: 0.1.0
Summary: Document image aUGmentation.
Home-page: UNKNOWN
Author: YuanGan Zhou, Zhen Qi, Nanxin Ning
Author-email: zqi@che300.com
License: UNKNOWN
Platform: UNKNOWN
Classifier: Intended Audience :: Developers
Classifier: Intended Audience :: Science/Research
Classifier: Operating System :: OS Independent
Classifier: Programming Language :: Python :: 3
Classifier: Topic :: Software Development :: Libraries :: Python Modules
Requires-Python: >=3.5
Requires-Dist: numpy (>=1.11.1)
Requires-Dist: opencv-python (>=3.4.2)
